{"hash":"d117acfb0559d945f2d7497a646345892b09150d","data":{"strapi":{"projects":[{"id":"612d05f3defbad14e4e71025","title":"All Publishing","slug":"all-publishing","description":"Développement d'un thème WordPress commun pour les différents magazines édités par All Publishing (ParisBerlin, AlgerParis, ParisMontréal, ParisCasablanca)","categories":[{"id":"60451b737cfc2616b89f3b29","title":"Développement"}],"technos":[{"id":"6045513ba2366f047440a08a","title":"WordPress"}],"projectLinks":[{"url":"https://parisberlinmag.com/"}],"coverImage":{"id":"612d05f1defbad14e4e71024","url":"/uploads/parisberlinmag_7ee9582796.JPG"},"content":[]}]}},"context":{"slug":"all-publishing"}}